{
  "id": 324,
  "query_string": null,
  "repository_id": 11,
  "repository_url": "https://www.fsd.tuni.fi/en",
  "project_url": "https://services.fsd.tuni.fi/catalogue/FSD2763",
  "version": null,
  "title": "Attitudes towards Corporal Punishment of Children in Finland 2012",
  "description": "The data are part of Central Union for Child Welfare study that investigates the use of corporal punishment in upbringing and attitudes towards it in Finland. Face-to-face interviews were carried out in spring 2012 as part of an Omnibus study monthly conducted by Taloustutkimus. The respondents were asked whether they thought corporal punishment was, at least in some cases, acceptable. The same question was asked about pulling a child's hair or flicking them. Further questions included whether u",
  "language": "fi, en",
  "doi": "https://doi.org/10.60686/t-fsd2763",
  "upload_date": "2012-10-10",
  "download_date": null,
  "download_repository_folder": "finnish-social-science-data-archive",
  "download_project_folder": "FSD2763",
  "download_version_folder": null,
  "download_method": "API-CALL",
  "license": "In accordance with the agreement between FSD and the depositor.",
  "license_url": null
}