{
  "id": 77,
  "query_string": null,
  "repository_id": 11,
  "repository_url": "https://www.fsd.tuni.fi/en",
  "project_url": "https://services.fsd.tuni.fi/catalogue/FSD2195",
  "version": null,
  "title": "Young Boys' Mobile Phone Use 2000-2002",
  "description": "The survey charted young boys' use of mobile phones in Finland. The archived data consist of interviews of young boys (aged around 13-16) between 2000 and 2002. Topics covered the use of mobile phones with friends, in everyday life and in school. The dataset comprises 26 interviews. The dataset is only available in Finnish.",
  "language": "fi, en",
  "doi": "https://doi.org/10.60686/t-fsd2195",
  "upload_date": "2007-06-26",
  "download_date": null,
  "download_repository_folder": "finnish-social-science-data-archive",
  "download_project_folder": "FSD2195",
  "download_version_folder": null,
  "download_method": "API-CALL",
  "license": "In accordance with the agreement between FSD and the depositor.",
  "license_url": null
}