<?xml version="1.0" encoding="utf-8"?>
<codeBook xmlns:xsi="http://www.w3.org/2001/XMLSchema-instance" xmlns="ddi:codebook:2_5" version="2.5" xsi:schemaLocation="ddi:codebook:2_5 http://www.ddialliance.org/Specification/DDI-Codebook/2.5/XMLSchema/codebook.xsd" xml:lang="fi">
  <docDscr>
    <citation>
      <titlStmt>
        <titl>DDI-kuvailu: Ydinjätepäätös 2001</titl>
        <parTitl xml:lang="en">DDI description: Decision on Final Disposal of Nuclear Waste 2001</parTitl>
        <IDNo agency="FSD">1249</IDNo>
      </titlStmt>
      <prodStmt>
        <producer abbr="FSD">Yhteiskuntatieteellinen tietoarkisto</producer>
        <copyright>Yhteiskuntatieteellinen tietoarkisto</copyright>
        <prodPlac>Yhteiskuntatieteellinen tietoarkisto</prodPlac>
      </prodStmt>
      <verStmt>
        <version date="2003-05-08" type="mef_fin">1.0.0</version>
      </verStmt>
      <biblCit>Ydinjätepäätös 2001 [metadata]. Metadataversio 1.0.0 (2003-05-08). Yhteiskuntatieteellinen tietoarkisto [tuottaja ja jakaja]. DOI: https://doi.org/10.60686/t-fsd1249; URN: https://urn.fi/urn:nbn:fi:fsd:T-FSD1249</biblCit>
      <holdings location="Yhteiskuntatieteellinen tietoarkisto FSD" URI="https://urn.fi/urn:nbn:fi:fsd:T-FSD1249" />
    </citation>
    <notes xml:lang="fi">FSD:n aineistokuvailut (FSD metadata records), joiden tekijä on Suomen yhteiskuntatieteellinen tietoarkisto (Finnish Social Science Data Archive), on lisensoitu Creative Commons 1.0 Yleismaailmallinen (CC0 1.0) -lisenssillä.
      <ExtLink URI="https://creativecommons.org/publicdomain/zero/1.0/deed.fi" />
    </notes>
    <notes xml:lang="en">FSD:n aineistokuvailut (FSD metadata records) by Suomen yhteiskuntatieteellinen tietoarkisto (Finnish Social Science Data Archive) are licensed under a Creative Commons 1.0 Universal (CC0 1.0) license.
      <ExtLink URI="https://creativecommons.org/publicdomain/zero/1.0/deed.en" />
    </notes>
    <notes xml:lang="sv">FSD:n aineistokuvailut (FSD metadata records) av Finlands samhällsvetenskapliga dataarkiv (Finnish Social Science Data Archive) är licensierade under en Creative Commons 1.0 Universiell (CC0 1.0) licens.
      <ExtLink URI="https://creativecommons.org/publicdomain/zero/1.0/deed.sv" />
    </notes>
  </docDscr>
  <stdyDscr>
    <citation>
      <titlStmt>
        <titl>Ydinjätepäätös 2001</titl>
        <altTitl>Ydinpolttoaineen loppusijoituslaitoksen rakentamisluvan päätösprosessi</altTitl>
        <parTitl xml:lang="en">Decision on Final Disposal of Nuclear Waste 2001</parTitl>
        <IDNo agency="FSD">1249</IDNo>
        <IDNo agency="URN">urn:nbn:fi:fsd:T-FSD1249</IDNo>
        <IDNo agency="DOI">10.60686/t-fsd1249</IDNo>
      </titlStmt>
      <rspStmt>
        <AuthEnty affiliation="Tampereen yliopisto. Politiikan tutkimuksen laitos">Suominen, Petteri</AuthEnty>
      </rspStmt>
      <prodStmt>
        <producer>Sanoma Osakeyhtiö</producer>
        <copyright>Tietoarkiston ja aineiston luovuttajan tekemän sopimuksen mukaisesti.</copyright>
      </prodStmt>
      <distStmt>
        <distrbtr abbr="FSD" URI="https://www.fsd.tuni.fi/">Yhteiskuntatieteellinen tietoarkisto</distrbtr>
        <distDate date="2003-05-08" />
      </distStmt>
      <serStmt ID="S8" URI="https://services.fsd.tuni.fi/catalogue/series/8?lang=fi">
        <serName>Aineistot, jotka eivät kuulu sarjaan</serName>
        <serInfo>
          <p>Yksittäiset aineistot, jotka eivät kuulu mihinkään sarjaan.</p>
        </serInfo>
      </serStmt>
      <verStmt>
        <version date="2003-05-08" type="main_data">1.0</version>
      </verStmt>
      <biblCit>Suominen, Petteri (Tampereen yliopisto): Ydinjätepäätös 2001 [data]. Dataversio 1.0 (2003-05-08). Yhteiskuntatieteellinen tietoarkisto [jakaja]. DOI: https://doi.org/10.60686/t-fsd1249; URN: https://urn.fi/urn:nbn:fi:fsd:T-FSD1249</biblCit>
      <holdings location="Yhteiskuntatieteellinen tietoarkisto FSD" URI="https://urn.fi/urn:nbn:fi:fsd:T-FSD1249" />
    </citation>
    <stdyInfo>
      <subject>
        <keyword vocab="YSO" vocabURI="http://www.yso.fi/onto/yso/">energiapolitiikka</keyword>
        <keyword vocab="YSO" vocabURI="http://www.yso.fi/onto/yso/">eduskuntatyö</keyword>
        <keyword vocab="YSO" vocabURI="http://www.yso.fi/onto/yso/">jätehuoltolaitokset</keyword>
        <keyword vocab="YSO" vocabURI="http://www.yso.fi/onto/yso/">ongelmajätelaitokset</keyword>
        <keyword vocab="YSO" vocabURI="http://www.yso.fi/onto/yso/">poliittinen päätöksenteko</keyword>
        <keyword vocab="YSO" vocabURI="http://www.yso.fi/onto/yso/">politiikka</keyword>
        <keyword vocab="YSO" vocabURI="http://www.yso.fi/onto/yso/">polttoaineet</keyword>
        <keyword vocab="YSO" vocabURI="http://www.yso.fi/onto/yso/">päästöt</keyword>
        <keyword vocab="YSO" vocabURI="http://www.yso.fi/onto/yso/">ydinenergia</keyword>
        <keyword vocab="YSO" vocabURI="http://www.yso.fi/onto/yso/">ydinjätteet</keyword>
        <keyword vocab="YSO" vocabURI="http://www.yso.fi/onto/yso/">ydinvoimalat</keyword>
        <keyword vocab="YSO" vocabURI="http://www.yso.fi/onto/yso/">ympäristö</keyword>
        <keyword vocab="YSO" vocabURI="http://www.yso.fi/onto/yso/">ympäristökuormitus</keyword>
        <keyword vocab="YSO" vocabURI="http://www.yso.fi/onto/yso/">ympäristöpolitiikka</keyword>
        <keyword>loppusijoituslaitos</keyword>
        <keyword>Teollisuuden Voima Oy</keyword>
        <keyword>Fortum Power and Heat Oy</keyword>
        <keyword>Posiva Oy</keyword>
        <keyword>Olkiluoto</keyword>
        <topcClas vocab="OKM" vocabURI="http://www.yso.fi/onto/okm-tieteenala/conceptscheme">Yhteiskuntatieteet</topcClas>
        <topcClas vocab="OKM" vocabURI="http://www.yso.fi/onto/okm-tieteenala/conceptscheme">Luonnontieteet</topcClas>
        <topcClas vocab="CESSDA Topic Classification" vocabURI="https://vocabularies.cessda.eu/urn/urn:ddi:int.cessda.cv:TopicClassification:4.2.3">Energia- ja luonnonvarat</topcClas>
        <topcClas vocab="CESSDA Topic Classification" vocabURI="https://vocabularies.cessda.eu/urn/urn:ddi:int.cessda.cv:TopicClassification:4.2.3">Poliittinen käyttäytyminen, poliittiset asenteet ja mielipiteet</topcClas>
        <topcClas vocab="CESSDA Topic Classification" vocabURI="https://vocabularies.cessda.eu/urn/urn:ddi:int.cessda.cv:TopicClassification:4.2.3">Ympäristönsuojelu ja ympäristöongelmat</topcClas>
      </subject>
      <abstract>
        <p>Aineisto sisältää viidennen ydinvoimalan puoltamispäätöstä edeltäneen ydinjätteen loppusijoituslaitoksen rakentamislupaa koskevia päätösasiakirjoja vuosilta 2000 ja 2001. Kyseessä on eduskunnan toukokuussa 2001 tekemä päätös, jonka mukaan valtioneuvoston periaatepäätös käytetyn ydinpolttoaineen loppusijoituksesta jäi voimaan. Valtioneuvoston periaatepäätös tehtiin joulukuussa 2000 ja ydinenergialain mukaisesti sen voimaan jääminen edellytti vielä eduskunnan hyväksymistä. Päätös eduskunnassa syntyi äänestyksen jälkeen. Ennen päätöstä asiasta teki eduskunnalle mietinnön eduskunnan talousvaliokunta, jolle puolestaan ympäristövaliokunta antoi ensin lausuntonsa.</p>
        <p>Aineisto koostuu päätöstä koskevista keskeisistä julkisista asiakirjoista ja asiasta käydyistä eduskuntakeskusteluista. Aikajärjestyksessä aineistoon kuuluvat: (1) Posiva Oy:n valtioneuvostolle osoitettu hakemus ja sen (2) liiteasiakirja 14 (suunnitelmat käytettävissä olevista menetelmistä ydinjätehuollon järjestämiseksi), (3) valtioneuvoston periaatepäätös käytetyn ydinpolttoaineen loppusijoituksesta, (4) asiasta helmikuussa 2001 käyty eduskunnan lähetekeskustelu, (5) ympäristövaliokunnan lausunto asiasta talousvaliokunnalle, (6) talousvaliokunnan mietintö eduskunnalle, (7) eduskunnan täysistuntokeskustelu ydinpolttoaineen loppusijoituslaitoksen rakentamisesta toukokuussa 2001.</p>
        <p>Eduskunnan lähete- ja täysistuntokeskusteluista ovat aineistossa mukana sanasta sanaan kirjattuna kaikki kansanedustajien puheenvuorot. Aineistoon kuuluvat myös keskusteluista tehdyt listaukset, joissa luetellaan puhujat ja heidän puheenvuorojensa määrä.</p>
      </abstract>
      <sumDscr>
        <timePrd event="start" date="2000" />
        <timePrd event="end" date="2001" />
        <collDate event="start" date="2000" />
        <collDate event="end" date="2001" />
        <nation abbr="FI">Suomi</nation>
        <geogCover>Suomi</geogCover>
        <anlyUnit>Tapahtuma/prosessi/toiminta
          <concept vocab="DDI Analysis Unit" vocabURI="https://vocabularies.cessda.eu/urn/urn:ddi:int.ddi.cv:AnalysisUnit:2.1.3">EventOrProcessOrActivity</concept>
        </anlyUnit>
        <anlyUnit>Mediatyyppi: teksti
          <concept vocab="DDI Analysis Unit" vocabURI="https://vocabularies.cessda.eu/urn/urn:ddi:int.ddi.cv:AnalysisUnit:2.1.3">MediaUnit.Text</concept>
        </anlyUnit>
        <universe>Viidennen ydinvoimalan puoltamispäätöstä edeltäneen ydinjätteen loppusijoituslaitoksen rakentamislupaa koskevat päätösasiakirjat vuosilta 2000 ja 2001 sekä päätöstä koskeneet eduskuntakäsittelyt</universe>
        <dataKind>Kvalitatiivinen</dataKind>
      </sumDscr>
    </stdyInfo>
    <method>
      <dataColl>
        <timeMeth>Poikkileikkausaineisto
          <concept vocab="DDI Time Method" vocabURI="https://vocabularies.cessda.eu/urn/urn:ddi:int.ddi.cv:TimeMethod:1.2.3">CrossSection</concept>
        </timeMeth>
        <dataCollector affiliation="Tampereen yliopisto. Politiikan tutkimuksen laitos">Suominen, Petteri</dataCollector>
        <sampProc>Ei-todennäköisyysotanta: harkinnanvarainen poiminta
          <concept vocab="DDI Sampling Procedure" vocabURI="https://vocabularies.cessda.eu/urn/urn:ddi:int.ddi.cv:SamplingProcedure:2.0.2">Nonprobability.Purposive</concept>
        </sampProc>
        <sampProc>
          <p>Tutkija on kerännyt aineistokseen kokonaisuuden, jonka varassa on ollut mahdollista tehdä ydinjätteen loppusijoitusta koskevasta päätöksenteosta argumentointianalyysi.</p>
        </sampProc>
        <collMode>Kooste- tai synteesiaineisto
          <concept vocab="DDI Mode of Collection" vocabURI="https://vocabularies.cessda.eu/urn/urn:ddi:int.ddi.cv:ModeOfCollection:5.0.1">CompilationSynthesis</concept>
        </collMode>
        <resInstru>Aineistonkeruuohjeistus: poimintaohje tai -suunnitelma
          <concept vocab="DDI Type of Instrument" vocabURI="https://vocabularies.cessda.eu/urn/urn:ddi:int.ddi.cv:TypeOfInstrument:1.1.2">DataCollectionGuidelines.SecondaryDataCollectionGuide</concept>
        </resInstru>
      </dataColl>
      <stdyClas type="A">Aineisto on kuvailtu mahdollisimman kattavasti suomeksi ja englanniksi. Aineisto on tarkistettu ja muokattu yksityiskohtaisesti. Tarvittaessa aineistosta on poistettu tunnisteita.</stdyClas>
    </method>
    <dataAccs>
      <setAvail>
        <accsPlac URI="https://www.fsd.tuni.fi/">Yhteiskuntatieteellinen tietoarkisto</accsPlac>
        <collSize>Yhteensä noin 150 tekstisivua</collSize>
      </setAvail>
      <useStmt>
        <restrctn>Aineisto on (A) vapaasti käytettävissä ilman rekisteröitymistä (CC BY 4.0).</restrctn>
        <citReq>Aineistoon ja sen tekijöihin tulee viitata asianmukaisesti kaikissa julkaisuissa ja esityksissä, joissa aineistoa käytetään. Tietoarkiston antaman malliviittaustiedon voi merkitä lähdeluetteloon sellaisenaan tai sitä voi muokata julkaisun käytäntöjen mukaisesti.</citReq>
        <deposReq>Viitetiedot julkaisuista, joissa aineistoa on käytetty, toimitetaan Tietoarkiston asiakaspalveluun asiakaspalvelu.fsd@tuni.fi.</deposReq>
        <disclaimer>Aineiston alkuperäiset tekijät ja Tietoarkisto eivät ole vastuussa aineiston jatkokäytössä tuotetuista tuloksista ja tulkinnoista.</disclaimer>
      </useStmt>
    </dataAccs>
    <othrStdyMat>
      <relPubl xml:lang="fi">Raittila, Pentti &amp; Suominen, Petteri (2002): Keskustelu ydinjätteen loppusijoitusta koskevasta periaatepäätöksestä eduskunnassa ja mediassa. Teoksessa Raittila, Hokkanen, Kojo &amp; Litmanen (toim): Ydinjäteihme suomalaisittain. Tampere University Press.
        <citation>
          <titlStmt>
            <titl>Keskustelu ydinjätteen loppusijoitusta koskevasta periaatepäätöksestä eduskunnassa ja mediassa</titl>
          </titlStmt>
          <distStmt>
            <distDate date="2002" />
          </distStmt>
        </citation>
      </relPubl>
      <relPubl xml:lang="fi">Suominen, Petteri (2002). Eduskunta jätteen ytimessä. Ydinjätteen loppusijoitusta koskevan eduskuntakäsittelyn argumentointianalyysia. JYT2001 tutkimuksia. Tampere: Tampereen yliopisto. Politiikan tutkimuksen laitos. Työraportti; 1/2002.
        <citation>
          <titlStmt>
            <titl>Eduskunta jätteen ytimessä. Ydinjätteen loppusijoitusta koskevan eduskuntakäsittelyn argumentointianalyysia</titl>
          </titlStmt>
          <distStmt>
            <distDate date="2002" />
          </distStmt>
        </citation>
      </relPubl>
    </othrStdyMat>
  </stdyDscr>
</codeBook>
