{
  "id": 384,
  "query_string": null,
  "repository_id": 11,
  "repository_url": "https://www.fsd.tuni.fi/en",
  "project_url": "https://services.fsd.tuni.fi/catalogue/FSD3126",
  "version": null,
  "title": "Interviews of Active Members of the Association for Cultural Workers in Finland 2012-2013",
  "description": "The data comprise interviews with active members in the former Association for Cultural Workers in Finland (Kulttuurity\u00f6ntekij\u00e4in liitto, KTL), which was a Finnish Marxist-Leninist association founded in 1972. All interviewees had had a significant role in the founding and activities of the association, and they appear in the data with their real names. The interview questions were structured around five main themes: personal background; motivations for participating in political activism and jo",
  "language": "fi, en",
  "doi": "https://doi.org/10.60686/t-fsd3126",
  "upload_date": "2018-08-07",
  "download_date": null,
  "download_repository_folder": "finnish-social-science-data-archive",
  "download_project_folder": "FSD3126",
  "download_version_folder": null,
  "download_method": "API-CALL",
  "license": "In accordance with the agreement between FSD and the depositor.",
  "license_url": null
}